setup.py
clixevolve/__init__.py
clixevolve/diff.py
clixevolve/extract_structure.py
clixevolve/migrate.py
clixevolve.egg-info/PKG-INFO
clixevolve.egg-info/SOURCES.txt
clixevolve.egg-info/dependency_links.txt
clixevolve.egg-info/entry_points.txt
clixevolve.egg-info/requires.txt
clixevolve.egg-info/top_level.txt