Metadata-Version: 1.0
Name: clixevolve
Version: 0.4dev
Summary: ClixEvolve -- the righteous schema evolver
Home-page: http://silassnider.com
Author: Silas Snider
Author-email: silas.snider@showclix.com
License: UNKNOWN
Platform: UNKNOWN
